{
    "poubelles": [
        {
            "couleur": "jaune",
            "description": "Emballages en verre, en métal et en plastique",
            "exemples": [
                "en:pet-polyethylene-terephthalate",
                "en:glass-jar",
                "en:glass-bottle",
                "en:clear-glass",
                "en:heavy-aluminium",
                "en:pet-bottle",
                "en:container",
                "en:plastic-bottle",
                "en:plastic",
                "en:green-dot",
                "en:pack",
                "en:hdpe-bottle",
                "en:card-sleeve",
                "en:aluminium-lid",
                "en:pet-tub",
                "en:plastic-bag",
                "en:steel-lid",
                "en:pet-lid",
                "en:pp-lid",
                "en:plastique",
                "en:Paper and cardboard / Plastic / Aluminium",
                "en:produkt",
                "en:metal-lid",
                "en:pet-pot",
                "en:plastic-lid",
                "en:verre",
                "en:jar-glass",
                "en:card-box",
                "en:pp-cap",
                "en:plastic-jar",
                "en:pp-pot",
                "en:Plastic/tinplate",
                "en:pp-tub",
                "en:product",
                "en:mixed-plastic-packet",
                "en:hdpe-lid",
                "en:flacon",
                "en:bouteille",
                "en:bottle-plastic",
                "en:pp-bottle",
                "en:ldpe-bag",
                "en:composite-carton",
                "en:stuck",
                "en:bottle-glass",
                "en:plastic-1",
                "en:card-tube",
                "en:mixed-plastic-film",
                "en:film-plastic",
                "en:tub",
                "en:cardboard-box",
                "en:other-plastic-lid",
                "en:bottle-s",
                "en:plastic-pouch",
                "en:kunststoff",
                "en:steel-tin",
                "en:plastic-shaker",
                "en:lid-metal",
                "en:aluminium-cap",
                "en:other-plastic-bottle",
                "en:pet-cap",
                "en:plastic-squeeze-bottle",
                "en:bocal",
                "en:bag-plastic",
                "en:glasflasche",
                "en:mixed-plastic-cap",
                "en:ldpe-film",
                "en:Tetra Brik Aseptic",
                "en:carton-card",
                "en:triman",
                "en:mixed-plastic-bag",
                "en:other-plastic-cap",
                "en:pet-tube",
                "en:metal-can",
                "en:plastic-tray",
                "en:lid-plastic",
                "en:boite",
                "en:steel-cap",
                "en:pot-plastic",
                "en:aluminium-can",
                "en:SIG",
                "en:item",
                "en:cap-metal",
                "en:pp-lid-and-cardboard-sleeve",
                "en:aluminium-tube",
                "en:papier",
                "en:pp-tube",
                "en:mixed-plastic-lid",
                "en:Tetra Brik",
                "en:1-plastic-bottle-to-recycle",
                "en:pet-tray",
                "en:plastic-film",
                "en:carton-box",
                "en:pet-seal",
                "en:paper-sleeve",
                "en:card-carton",
                "en:hdpe-cap",
                "en:round-pp-pot",
                "en:plastic-cap",
                "en:mixed-plastic-bottle",
                "en:1-glass-bottle-to-recycle",
                "en:flasche",
                "en:premium-glass-jar-with-bpa-free-mill",
                "en:steel-can",
                "en:knijpfles",
                "en:400-gr",
                "en:etui-en-carton",
                "en:plastic-pot",
                "en:cardboard-sleeve",
                "en:1-metal-lid",
                "en:brique",
                "en:1-metal-lid-to-recycle",
                "en:plastic-tube",
                "en:1-glass-jar",
                "en:1-metal-cap-for-recycling",
                "en:mixed-plastic-film-bag",
                "en:1-glass-bottle",
                "en:bouteille-en-plastique",
                "en:foil-wrapper",
                "en:flacon-en-plastique",
                "en:tarrina",
                "en:bouteille-en-verre",
                "en:pot-en-plastique",
                "en:couvercle-en-plastique",
                "en:couvercle-en-métal",
                "en:couvercle-en-aluminium",
                "en:poche-en-plastique",
                "en:film-en-plastique",
                "en:sachets-en-plastique",
                "en:boîte-en-carton",
                "en:autres-couvercles-en-plastique",
                "en:bouteilles-en-plastique",
                "en:flacons-en-plastique",
                "en:pochettes-en-plastique",
                "en:bouteilles-en-verre",
                "en:pots-en-plastique"
            ]
        },
        {
            "couleur": "Bleu",
            "description": "Papier et carton",
            "exemples": [
                "en:Paper and cardboard",
                "en:card-sleeve",
                "en:card-box",
                "en:card-tube",
                "en:carton-card",
                "en:carton-box",
                "en:card-carton",
                "en:cardboard-sleeve",
                "en:cardboard-box",
                "en:composite-carton",
                "en:paper-sleeve",
                "en:etui-en-carton",
                "en:papier"
            ]
        },
        {
            "couleur": "Gris",
            "description": "Déchets ménagers et équipements",
            "exemples": [
                "en:pp-bottle",
                "en:other-plastic-lid",
                "en:1-plastic-bottle-to-recycle",
                "en:flaccone",
                "en:producto",
                "en:97-glass-tinplate",
                "en:aluminium-cap",
                "en:flasque",
                "en:corked-bottle",
                "en:mixed-plastic-film-packet",
                "en:pet-cap",
                "en:botella",
                "en:tube-plastique",
                "en:capsule-en-metal",
                "en:plastic-bottle-and-bag",
                "en:1-metal-cap-to-recycle",
                "en:kunststofffolie",
                "en:etui-carton",
                "en:slim-glas",
                "en:flasche",
                "en:foil-wrapper",
                "en:1-glass-bottle-to-recycle",
                "en:mixed-plastic-packet",
                "en:g",
                "en:1-plastic-lid-to-recycle",
                "en:briquette",
                "en:pp-film-bag",
                "en:pladtic-bottle",
                "en:botellas",
                "en:square",
                "en:tin",
                "en:chartreuse-pretty",
                "en:small-bottle",
                "en:aluminium-tube",
                "en:portie",
                "en:hdpe-unknown",
                "en:film-en-plastique",
                "en:bouchon-de-bouteille",
                "en:plastique-pet",
                "en:tube-en",
                "en:barquette",
                "en:moulin",
                "en:tidyman-recycling",
                "en:aluminium-can-to-recycle",
                "en:metal-can",
                "en:metal-tin",
                "en:aluminium-foil",
                "en:aluminium-tray"
            ]
        },
        {
            "couleur": "Marrons",
            "description": "Déchets organiques",
            "exemples": [
                "en:green-dot",
                "en:produkt",
                "en:item"
            ]
        }
    ]
}